<?xml version="1.0" encoding="ISO-8859-1"?><MonitoringCompany><CompanyBriefHeading><CompanyName>GRANDOLFO STELIO DI GRANDOLFO MARCO &amp; CO.</CompanyName><LegalForm LegalFormCode="AS" LegalFormDescription="S.a.s." LegalFormType="P">SOCIETA' IN ACCOMANDITA SEMPLICE</LegalForm><Address><PostCode>34123</PostCode><Province Code="TS"/><Street>VIA OTTAVIANO AUGUSTO 12</Street><Municipality>TRIESTE</Municipality><Country>ITALIA</Country></Address><TaxCode>00961330321</TaxCode><ReaCode><CoCProvinceCode>TS</CoCProvinceCode><REANo>113829</REANo></ReaCode><CompanySituation Code="A">ATTIVA</CompanySituation><ActiveOnTheMarketSince day="29" hour24="0" minutes="0" month="12" seconds="0" year="1998">1998-12-29+01:00</ActiveOnTheMarketSince><EquityCapital>45958</EquityCapital><ActivityStatusStartDate day="20" hour24="0" minutes="0" month="1" seconds="0" year="1999">1999-01-20+01:00</ActivityStatusStartDate></CompanyBriefHeading><DeliveryAndSummaryDetails><Reference>Documento acquistato per valutazione CDS</Reference><CervedGroupCode>5550642</CervedGroupCode><RequestedService>Global Profile</RequestedService><MonitoringType>C</MonitoringType><MonitoringDate day="1" hour24="0" minutes="0" month="12" seconds="0" year="2015">2015-12-01+01:00</MonitoringDate><ProductCode>55220</ProductCode></DeliveryAndSummaryDetails><Synthesis><MonitoringType>C</MonitoringType><MonetReportOutput><idSoggetto>5550642</idSoggetto><codiceFiscale>00961330321</codiceFiscale><denominazione>GRANDOLFO STELIO DI GRANDOLFO MARCO &amp; CO. - SOCIETA' IN ACCOMANDITA SEMPLICE</denominazione><partitaIva>00961330321</partitaIva><cciaa>TS</cciaa><nrea>113829</nrea><idRichiesta>1549601292</idRichiesta><riferimento>Documento acquistato per valutazione CDS</riferimento><dtScadenza>2015-12-01T00:00:00.000+01:00</dtScadenza><tipoMonitoraggio>55220</tipoMonitoraggio><descrizione>Monitoraggio Global Profile</descrizione><MonetReportSintesi><classeSegnalazione>N</classeSegnalazione><descrizioneClasseSegnalazione>Evento Negativo</descrizioneClasseSegnalazione><MonetReportSegnalazione id="1"><gravita>H</gravita><tipoEvento>PL003</tipoEvento><descrizioneEvento>Variazione Negativa Grading Esperienze Pagamento</descrizioneEvento><data>2014-12-04T00:00:00.000+01:00</data><nuovoReport>true</nuovoReport></MonetReportSegnalazione></MonetReportSintesi><MonetReportDettaglio id="1"><classeSegnalazione>N</classeSegnalazione><gravita>H</gravita><data>2014-12-04T00:00:00.000+01:00</data><areaEvento>PL</areaEvento><tipoEvento>PL003</tipoEvento><descrizioneClasseSegnalazione>Evento Negativo</descrizioneClasseSegnalazione><descrizioneEvento>Variazione Negativa Grading Esperienze Pagamento</descrizioneEvento><idConsegna>0</idConsegna><idConsegnaFinita>0</idConsegnaFinita><InfoPayline><valoreSucc>27</valoreSucc><classePrec>5</classePrec><classeSucc>6</classeSucc></InfoPayline></MonetReportDettaglio><AnagraficaAzienda><denominazione>GRANDOLFO STELIO DI GRANDOLFO MARCO &amp; CO. - SOCIETA' IN ACCOMANDITA SEMPLICE</denominazione><dtModifica>2014-09-23T00:00:00.000+02:00</dtModifica><idSoggetto>5550642</idSoggetto><indirizzo><idIndirizzo>83861804</idIndirizzo><idIndirizzoNorm>80735998</idIndirizzoNorm><origine>I</origine><toponimo>VIA</toponimo><indirizzo>AUGUSTO OTTAVIANO</indirizzo><numeroCivico>12</numeroCivico><cap>34123</cap><cdComune>TS006</cdComune><comune>TRIESTE</comune><siglaProvincia>TS</siglaProvincia><provincia>Trieste</provincia><cdRegione>06</cdRegione><regione>Friuli Venezia Giulia</regione><cdRipartizioneGeo>ITD</cdRipartizioneGeo><ripartizioneGeo>Nord-est</ripartizioneGeo><presenzaDistretto>false</presenzaDistretto><coordinateGeografiche><idGeo>1</idGeo><idIndirizzo>83861804</idIndirizzo><latitudine>870582</latitudine><longitudine>5065770</longitudine><precisione>C</precisione><geoCodifica>UTM</geoCodifica></coordinateGeografiche><coordinateGeografiche><idGeo>2</idGeo><idIndirizzo>83861804</idIndirizzo><latitudine>45.64639</latitudine><longitudine>13.7558</longitudine><precisione>C</precisione><geoCodifica>WGS</geoCodifica></coordinateGeografiche></indirizzo><tipo>S</tipo><iscrittaCGR>true</iscrittaCGR><cciaa>TS</cciaa><classeNaturaGiuridica>SP</classeNaturaGiuridica><codiceFiscale>00961330321</codiceFiscale><consorzio>N</consorzio><descrNaturaGiuridica>SOCIETA' IN ACCOMANDITA SEMPLICE</descrNaturaGiuridica><dtCostituzione>1998-12-29T00:00:00.000+01:00</dtCostituzione><dtInizioAttivita>1999-01-20T00:00:00.000+01:00</dtInizioAttivita><dtInizioStatoAttivita>1999-01-20T00:00:00.000+01:00</dtInizioStatoAttivita><dtIscrizione>1999-01-20T00:00:00.000+01:00</dtIscrizione><eta>15</eta><etaCgr>16</etaCgr><FNatGiuCGR>1</FNatGiuCGR><naturaGiuridica>AS</naturaGiuridica><nrea>113829</nrea><partitaIva>00961330321</partitaIva><siglaNaturaGiuridica>S.a.s.</siglaNaturaGiuridica><statoAttivita>A</statoAttivita><etaMesi>191</etaMesi></AnagraficaAzienda><tipoRichiesta>C</tipoRichiesta></MonetReportOutput></Synthesis><HistoricalRiskEvaluation><MonitoringType>C</MonitoringType><Evaluations><Label>0</Label></Evaluations><Evaluations><Label>1</Label></Evaluations><Evaluations><Label>2</Label></Evaluations><Evaluations><Label>3</Label></Evaluations><Evaluations><Label>4</Label></Evaluations><Evaluations><Label>5</Label></Evaluations><Evaluations><Label>6</Label></Evaluations><Evaluations><Label>7</Label></Evaluations><Evaluations><Label>8</Label></Evaluations><Evaluations><Label>9</Label></Evaluations><Evaluations><Label>10</Label></Evaluations><Evaluations CurrentMonth="1"><Label>11</Label><Value>20110000</Value><Risk>4</Risk><RatingType>CGR</RatingType></Evaluations></HistoricalRiskEvaluation></MonitoringCompany>